hailuo_tts/__init__.py
hailuo_tts/tts.py
hailuo_tts/voice_clone.py
hailuo_tts_api-0.0.2.dist-info/METADATA
hailuo_tts_api-0.0.2.dist-info/WHEEL
hailuo_tts_api-0.0.2.dist-info/RECORD
