Metadata-Version: 2.4
Name: hailuo-tts-api
Version: 0.0.2
Summary: A simple Wrapper for Hailuo TTS
Project-URL: Homepage, https://github.com/daswer123/hailuo-tts-api
Project-URL: Bug Tracker, https://github.com/daswer123/hailuo-tts-api/issues
Author-email: daswer123 <daswerq123@gmail.com>
Classifier: License :: OSI Approved :: MIT License
Classifier: Operating System :: OS Independent
Classifier: Programming Language :: Python :: 3
Requires-Python: >=3.9
Requires-Dist: requests
Requires-Dist: uuid
